async_bitmex_ws/__init__.py
async_bitmex_ws/async_bitmex_ws.py
async_bitmex_ws-1.0.1.dist-info/LICENSE
async_bitmex_ws-1.0.1.dist-info/METADATA
async_bitmex_ws-1.0.1.dist-info/WHEEL
async_bitmex_ws-1.0.1.dist-info/top_level.txt
async_bitmex_ws-1.0.1.dist-info/RECORD
