Metadata-Version: 2.1
Name: async-bitmex-ws
Version: 1.0.1
Summary: Asynchronous bitmex websocket api development kit
Home-page: https://github.com/monk-after-90s/async_bitmex_ws.git
Author: Antas
Author-email: 
License: UNKNOWN
Platform: UNKNOWN
Classifier: Programming Language :: Python :: 3
Classifier: License :: OSI Approved :: MIT License
Classifier: Operating System :: OS Independent
Requires-Python: >=3.6
